privacy/__init__.py
privacy/api_client.py
privacy/http_client.py
privacy/schema/__init__.py
privacy/schema/base.py
privacy/schema/cards.py
privacy/schema/embeds.py
privacy/schema/events.py
privacy/schema/fundings.py
privacy/schema/merchants.py
privacy/schema/transactions.py
privacy/util/__init__.py
privacy/util/functional.py
privacy/util/json.py
privacy/util/logging.py
privacy/util/pagination.py
privacy/util/webhook.py
privacy.py-2019.12.11.dist-info/LICENSE
privacy.py-2019.12.11.dist-info/WHEEL
privacy.py-2019.12.11.dist-info/METADATA
privacy.py-2019.12.11.dist-info/RECORD
