Metadata-Version: 2.1
Name: privacy.py
Version: 2019.12.11
Summary: A Python lib for Privacy.com
Home-page: https://github.com/FasterSpeeding/Privacy.py
License: BSD-3-Clause
Author: FasterSpeeding
Author-email: Luke@lmbyrne.dev
Requires-Python: >=3.6,<3.9
Classifier: Development Status :: 2 - Pre-Alpha
Classifier: Intended Audience :: Developers
Classifier: License :: OSI Approved :: BSD License
Classifier: Natural Language :: English
Classifier: Operating System :: OS Independent
Classifier: Programming Language :: Python :: 3
Classifier: Programming Language :: Python :: 3.6
Classifier: Programming Language :: Python :: 3.7
Classifier: Programming Language :: Python :: 3.8
Classifier: Topic :: Internet
Classifier: Topic :: Software Development :: Libraries
Classifier: Topic :: Software Development :: Libraries :: Python Modules
Classifier: Topic :: Utilities
Requires-Dist: pydantic (==1.0)
Requires-Dist: requests (==2.22.0)
Project-URL: Repository, https://github.com/FasterSpeeding/Privacy.py
